orthanc_rest_client/VERSION
orthanc_rest_client/__init__.py
orthanc_rest_client/orthanc.py
orthanc_rest_client/endpoints/__init__.py
orthanc_rest_client/endpoints/instances.py
orthanc_rest_client/endpoints/misc.py
orthanc_rest_client/endpoints/modalities.py
orthanc_rest_client/endpoints/patients.py
orthanc_rest_client/endpoints/queries.py
orthanc_rest_client/endpoints/series.py
orthanc_rest_client/endpoints/studies.py
orthanc_rest_client-0.5.7.dist-info/METADATA
orthanc_rest_client-0.5.7.dist-info/RECORD
orthanc_rest_client-0.5.7.dist-info/WHEEL
orthanc_rest_client-0.5.7.dist-info/top_level.txt
