Metadata-Version: 2.1
Name: orthanc-rest-client
Version: 0.5.7
Summary: REST client for Orthanc DICOM servers
Home-page: https://github.com/teffalump/orthanc_rest_client
Author: teffalump
Author-email: chris@teffalump.com
License: UNKNOWN
Platform: UNKNOWN
Classifier: Development Status :: 4 - Beta
Classifier: Programming Language :: Python :: 3
Classifier: Programming Language :: Python :: 3 :: Only
Classifier: Intended Audience :: Developers
Classifier: License :: OSI Approved :: GNU General Public License v3 or later (GPLv3+)
Classifier: Operating System :: OS Independent
